simple_dotenv/__init__.py
simple_dotenv/simple_dotenv.py
simple_dotenv-0.1.4.dist-info/LICENSE.txt
simple_dotenv-0.1.4.dist-info/METADATA
simple_dotenv-0.1.4.dist-info/WHEEL
simple_dotenv-0.1.4.dist-info/top_level.txt
simple_dotenv-0.1.4.dist-info/RECORD
